dove/__init__.py
dove/dove.py
dove/core/__init__.py
dove/core/infamilyanalysis.py
dove/core/multigenomeanalysis.py
dove/core/onlinevariantannotation.py
dove/core/variantfilter.py
dove/examples/__init__.py
dove/examples/examplefilter.txt
dove/examples/examplepedigree.csv
dove/utils/__init__.py
dove/utils/bed.py
dove/utils/copyexamplefiles.py
dove/utils/ensemblapi.py
dove/utils/parsefilterfile.py
dove/utils/parsepedigree.py
dove/utils/parsevcf.py
dove/utils/updateclinvar.py
dove/utils/updatehpo.py
dove/utils/updateomim.py
dove/utils/vcf.py
dove/utils/vcfdbmodel.py
seq_dove-0.4.4.dist-info/LICENSE
seq_dove-0.4.4.dist-info/METADATA
seq_dove-0.4.4.dist-info/WHEEL
seq_dove-0.4.4.dist-info/entry_points.txt
seq_dove-0.4.4.dist-info/top_level.txt
seq_dove-0.4.4.dist-info/RECORD
