Metadata-Version: 2.1
Name: seq-dove
Version: 0.4.4
Summary: Set of tools for downstream vcf analysis
Home-page: UNKNOWN
Author: bars
Author-email: barslmn@gmail.com
License: UNKNOWN
Keywords: genomics next generation sequencing variant discovery human genetics
Platform: UNKNOWN
Classifier: Development Status :: 3 - Alpha
Classifier: Intended Audience :: Developers
Classifier: Topic :: Software Development :: Build Tools
Classifier: License :: OSI Approved :: MIT License
Classifier: Programming Language :: Python :: 3
Requires-Dist: pandas
Requires-Dist: responses
